resumable/__init__.py
resumable/chunk.py
resumable/core.py
resumable/file.py
resumable/util.py
resumable/version.py
resumable-0.1.1.dist-info/DESCRIPTION.rst
resumable-0.1.1.dist-info/LICENSE.txt
resumable-0.1.1.dist-info/METADATA
resumable-0.1.1.dist-info/RECORD
resumable-0.1.1.dist-info/WHEEL
resumable-0.1.1.dist-info/metadata.json
resumable-0.1.1.dist-info/top_level.txt
