Metadata-Version: 2.0
Name: resumable
Version: 0.1.1
Summary: Python client for upload to a server supporting resumable.js
Home-page: https://acroz.github.com/acroz/resumable.py
Author: Andrew Crozier
Author-email: wacrozier@gmail.com
License: MIT
Platform: UNKNOWN
Classifier: License :: OSI Approved :: MIT License
Classifier: Programming Language :: Python :: 2
Classifier: Programming Language :: Python :: 3
Requires-Dist: requests
Requires-Dist: futures
